Metadata-Version: 2.1
Name: crowdbotsimcontrol-ethrl
Version: 0.1.0
Summary: python API to control CrowdBotSim executable - updated for use with ETH RL projects
Home-page: UNKNOWN
Author: Daniel Dugas
Author-email: exodaniel@gmail.com
License: TODO
Platform: UNKNOWN
License-File: LICENSE
